teslapython/__init__.py
teslapython/main.py
teslapython/test_video.py
teslapython-0.1.20.dist-info/METADATA
teslapython-0.1.20.dist-info/WHEEL
teslapython-0.1.20.dist-info/entry_points.txt
teslapython-0.1.20.dist-info/top_level.txt
teslapython-0.1.20.dist-info/RECORD
