Metadata-Version: 2.4
Name: teslapython
Version: 0.1.20
Author: TeslaPython Software Foundation
Dynamic: author
Dynamic: description
Dynamic: description-content-type
